README.md
setup.cfg
setup.py
examples/__init__.py
examples/async/__init__.py
examples/async/create.py
examples/async/info.py
examples/async/verify.py
examples/sync/__init__.py
examples/sync/create.py
examples/sync/info.py
examples/sync/verify.py
pc4store/__init__.py
pc4store/config.py
pc4store/data.py
pc4store/exceptions.py
pc4store.egg-info/PKG-INFO
pc4store.egg-info/SOURCES.txt
pc4store.egg-info/dependency_links.txt
pc4store.egg-info/requires.txt
pc4store.egg-info/top_level.txt
pc4store/clients/__init__.py
pc4store/clients/asynchronous.py
pc4store/clients/base.py
pc4store/clients/sync.py
tests/utils/__init__.py
tests/utils/fixtures.py