Metadata-Version: 2.1
Name: pc4store
Version: 1.0.0
Summary: Python lib for integration with pc4store payment system
Home-page: UNKNOWN
License: MIT
Platform: UNKNOWN
